Metadata-Version: 2.4
Name: ai-helpers-yahwin
Version: 0.0.1
Summary: AI helper functions
Author: Your Name
License-File: LICENSE
Requires-Dist: requests
Dynamic: license-file
